setup.py
distributions/Binomialdistribution.py
distributions/Gaussiandistribution.py
distributions/Generaldistribution.py
distributions/__init__.py
kwakse_distributions.egg-info/PKG-INFO
kwakse_distributions.egg-info/SOURCES.txt
kwakse_distributions.egg-info/dependency_links.txt
kwakse_distributions.egg-info/not-zip-safe
kwakse_distributions.egg-info/top_level.txt