Metadata-Version: 1.0
Name: kwakse-distributions
Version: 1.0
Summary: Gaussian and Binomial Distributions
Home-page: UNKNOWN
Author: Joshua Boateng
Author-email: UNKNOWN
License: UNKNOWN
Platform: UNKNOWN
